lnmarkets_sdk/py.typed
lnmarkets_sdk/v3/_internal/__init__.py
lnmarkets_sdk/v3/_internal/models.py
lnmarkets_sdk/v3/_internal/utils.py
lnmarkets_sdk/v3/http/client/__init__.py
lnmarkets_sdk/v3/http/client/account.py
lnmarkets_sdk/v3/http/client/oracle.py
lnmarkets_sdk/v3/http/client/synthetic_usd.py
lnmarkets_sdk/v3/http/client/futures/__init__.py
lnmarkets_sdk/v3/http/client/futures/cross.py
lnmarkets_sdk/v3/http/client/futures/isolated.py
lnmarkets_sdk/v3/models/account.py
lnmarkets_sdk/v3/models/funding_fees.py
lnmarkets_sdk/v3/models/futures_cross.py
lnmarkets_sdk/v3/models/futures_data.py
lnmarkets_sdk/v3/models/futures_isolated.py
lnmarkets_sdk/v3/models/oracle.py
lnmarkets_sdk/v3/models/synthetic_usd.py
lnmarkets_sdk/v3/tests/test_integration.py
lnmarkets_sdk-0.0.19.dist-info/METADATA
lnmarkets_sdk-0.0.19.dist-info/WHEEL
lnmarkets_sdk-0.0.19.dist-info/licenses/LICENSE
lnmarkets_sdk-0.0.19.dist-info/RECORD
