Metadata-Version: 2.4
Name: lnmarkets-sdk
Version: 0.0.19
Summary: LN Markets API Python SDK
Project-URL: Homepage, https://github.com/ln-markets/sdk-python
Project-URL: Repository, https://github.com/ln-markets/sdk-python
Project-URL: Bug Tracker, https://github.com/ln-markets/sdk-python/issues
Author-email: K <kha.nguyen@ito.am>
License: MIT
License-File: LICENSE
Keywords: api,bitcoin,futures,lightning,lnmarkets,network,options,rest,trading
Classifier: Development Status :: 4 - Beta
Classifier: Intended Audience :: Developers
Classifier: License :: OSI Approved :: MIT License
Classifier: Operating System :: OS Independent
Classifier: Programming Language :: Python :: 3.12
Classifier: Programming Language :: Python :: 3.13
Classifier: Programming Language :: Python :: 3.14
Classifier: Topic :: Software Development :: Libraries :: Python Modules
Requires-Python: >=3.12
Requires-Dist: httpx>=0.28.1
Requires-Dist: pydantic>=2.12.2
Requires-Dist: requests>=2.32.3
